{
  "id": "cjpx7ihh90b430170fp6yjx37",
  "title": "The Cycle of Binge Eating",
  "module": {
    "id": "cjpx73xve09ym0170g0vrere2",
    "name": "Week 1",
    "eTherapy": {
      "id": "cjpx72o8j09tc0134xhgxl9mn",
      "name": "BEeT"
    }
  },
  "slides": [
    {
      "subtitle": "New Lesson",
      "isTitleSlide": true,
      "eLibraryTags": [],
      "isHidden": null,
      "settingAddToResources": null,
      "githubFileName": null,
      "key": "cjpx73xve09ym0170g0vrere2 3532737915 Title Slide",
      "content": {},
      "orderIndex": null,
      "previewURL": null,
      "slideType": {
        "name": "title_slide"
      },
      "title": "The Cycle of Binge Eating"
    },
    {
      "subtitle": "",
      "isTitleSlide": false,
      "eLibraryTags": [],
      "isHidden": false,
      "settingAddToResources": false,
      "githubFileName": null,
      "key": "cjpx7ihh90b430170fp6yjx37Overcoming Binge Eating1",
      "content": {
        "media": {
          "type": "video",
          "url": "https://vimeo.com/119074875",
          "caption": "Claudia explains why people develop binge eating habits."
        }
      },
      "orderIndex": null,
      "previewURL": "",
      "slideType": {
        "name": "media"
      },
      "title": "Overcoming Binge Eating"
    },
    {
      "subtitle": "",
      "isTitleSlide": false,
      "eLibraryTags": [],
      "isHidden": false,
      "settingAddToResources": false,
      "githubFileName": null,
      "key": "cjpx7ihh90b430170fp6yjx37Overcoming Binge Eating2",
      "content": {
        "media": {
          "type": "video",
          "url": "https://vimeo.com/119078692",
          "caption": "Listen to Alex talk about how he felt when he first started treatment."
        }
      },
      "orderIndex": null,
      "previewURL": "",
      "slideType": {
        "name": "media"
      },
      "title": "Overcoming Binge Eating"
    },
    {
      "subtitle": "",
      "isTitleSlide": false,
      "eLibraryTags": [],
      "isHidden": false,
      "settingAddToResources": false,
      "githubFileName": null,
      "key": "cjpx7ihh90b430170fp6yjx37Overcoming Binge Eating3",
      "content": {
        "interactive": {
          "type": "multiple_free_text",
          "columns": [
            "1. Before a binge\n\nDid something happen to upset you? Were you feeling overwhelmed by emotion?",
            "2. During a binge\n\nDid you feel as though you had lost all control?",
            "3. After a binge\n\nWere you feeling ashamed or embarassed? Did you do something to make up for the binge?"
          ]
        }
      },
      "orderIndex": null,
      "previewURL": "",
      "slideType": {
        "name": "interactive_multiple_free_text"
      },
      "title": "Overcoming Binge Eating"
    }
  ]
}